hopprcop/__init__.py
hopprcop/combined/__init__.py
hopprcop/combined/cli.py
hopprcop/combined/combined_scanner.py
hopprcop/combined/py.typed
hopprcop/enhancements/analysis_assessment.py
hopprcop/enhancements/epss/__init__.py
hopprcop/enhancements/epss/models.py
hopprcop/enhancements/epss_enhancer.py
hopprcop/gemnasium/__init__.py
hopprcop/gemnasium/gemnasium_scanner.py
hopprcop/gemnasium/models.py
hopprcop/gemnasium/py.typed
hopprcop/gemnasium/semver
hopprcop/grype/__init__.py
hopprcop/grype/grype_scanner.py
hopprcop/grype/py.typed
hopprcop/hoppr_plugin/__init__.py
hopprcop/hoppr_plugin/hopprcop_plugin.py
hopprcop/hoppr_plugin/py.typed
hopprcop/ossindex/README.md
hopprcop/ossindex/__init__.py
hopprcop/ossindex/api/__init__.py
hopprcop/ossindex/api/exception.py
hopprcop/ossindex/api/model.py
hopprcop/ossindex/api/ossindex.py
hopprcop/ossindex/api/py.typed
hopprcop/ossindex/api/serializer.py
hopprcop/ossindex/oss_index_scanner.py
hopprcop/ossindex/py.typed
hopprcop/py.typed
hopprcop/reporting/__init__.py
hopprcop/reporting/gitlab/__init__.py
hopprcop/reporting/gitlab/models.py
hopprcop/reporting/models.py
hopprcop/reporting/py.typed
hopprcop/reporting/templates/assets/vulnerabilities.css
hopprcop/reporting/templates/package-lock.json
hopprcop/reporting/templates/package.json
hopprcop/reporting/templates/tailwind.config.js
hopprcop/reporting/templates/vulnerabilities.html
hopprcop/reporting/templates/vulnerability.css
hopprcop/reporting/templates/vulnerability_details.html
hopprcop/trivy/__init__.py
hopprcop/trivy/py.typed
hopprcop/trivy/trivy_scanner.py
hopprcop/utils.py
hopprcop/vulnerability_combiner.py
hopprcop/vulnerability_enhancer.py
hopprcop/vulnerability_scanner.py
hoppr_cop-2.0.0.dist-info/METADATA
hoppr_cop-2.0.0.dist-info/WHEEL
hoppr_cop-2.0.0.dist-info/entry_points.txt
hoppr_cop-2.0.0.dist-info/licenses/LICENSE.md
hoppr_cop-2.0.0.dist-info/RECORD
