Metadata-Version: 2.4
Name: hoppr-cop
Version: 2.0.0
Summary: 
License: MIT
License-File: LICENSE.md
Author: kganger
Author-email: keith.e.ganger@lmco.com
Requires-Python: >=3.10,<4.0
Classifier: Development Status :: 3 - Alpha
Classifier: Intended Audience :: Developers
Classifier: Intended Audience :: Information Technology
Classifier: Intended Audience :: System Administrators
Classifier: License :: OSI Approved :: MIT License
Classifier: Programming Language :: Python
Classifier: Programming Language :: Python :: 3
Classifier: Programming Language :: Python :: 3.10
Classifier: Programming Language :: Python :: 3.11
Classifier: Programming Language :: Python :: 3.12
Classifier: Programming Language :: Python :: 3.13
Classifier: Programming Language :: Python :: 3.14
Classifier: Topic :: Communications :: File Sharing
Classifier: Topic :: Security
Classifier: Topic :: Software Development :: Version Control
Classifier: Topic :: System :: Archiving :: Packaging
Classifier: Topic :: System :: Software Distribution
Classifier: Typing :: Typed
Requires-Dist: PyYAML (>=6.0,<7.0)
Requires-Dist: cvss (>=3.0,<4.0)
Requires-Dist: hoppr (==1.14.1)
Requires-Dist: packageurl-python (==0.*)
Requires-Dist: packaging (>=24.1,<25.0)
Requires-Dist: rich (>12.5.1)
Requires-Dist: tinydb (>=4.7.0,<5.0.0)
Requires-Dist: typer (==0.*)
Requires-Dist: typing-extensions (>=4.8.0,<5.0.0)
